{
  "engine": "docling",
  "entries": [
    {
      "id": "docling-eq-0001",
      "kind": "display",
      "display_latex": "M = (m | m is a valid model and has topological structure G(mo)}. (1)",
      "semantic_expr": null,
      "compiled_targets": {},
      "conversion": {
        "status": "unconverted",
        "notes": ""
      },
      "source_spans": [
        {
          "page": 5,
          "bbox": {
            "x0": 101.01,
            "y0": 374.15,
            "x1": 644.16,
            "y1": 392.36,
            "width": 543.15,
            "height": 18.21
          },
          "engine": "docling"
        }
      ],
      "alternates": [],
      "review": {
        "status": "unreviewed",
        "risk": "medium",
        "notes": ""
      },
      "equation_number": "(1)"
    },
    {
      "id": "docling-eq-0002",
      "kind": "display",
      "display_latex": "(2)",
      "semantic_expr": null,
      "compiled_targets": {},
      "conversion": {
        "status": "unconverted",
        "notes": ""
      },
      "source_spans": [
        {
          "page": 11,
          "bbox": {
            "x0": 619.32,
            "y0": 650.62,
            "x1": 640.85,
            "y1": 665.52,
            "width": 21.53,
            "height": 14.9
          },
          "engine": "docling"
        }
      ],
      "alternates": [],
      "review": {
        "status": "unreviewed",
        "risk": "medium",
        "notes": ""
      },
      "equation_number": "(2)"
    },
    {
      "id": "docling-eq-0003",
      "kind": "display",
      "display_latex": "(3)",
      "semantic_expr": null,
      "compiled_targets": {},
      "conversion": {
        "status": "unconverted",
        "notes": ""
      },
      "source_spans": [
        {
          "page": 11,
          "bbox": {
            "x0": 619.32,
            "y0": 758.23,
            "x1": 640.85,
            "y1": 774.78,
            "width": 21.53,
            "height": 16.55
          },
          "engine": "docling"
        }
      ],
      "alternates": [],
      "review": {
        "status": "unreviewed",
        "risk": "medium",
        "notes": ""
      },
      "equation_number": "(3)"
    },
    {
      "id": "docling-eq-0004",
      "kind": "display",
      "display_latex": "Фе (е)к. , Є!к) > Фе (cl,2, е.).",
      "semantic_expr": null,
      "compiled_targets": {},
      "conversion": {
        "status": "unconverted",
        "notes": ""
      },
      "source_spans": [
        {
          "page": 11,
          "bbox": {
            "x0": 233.49,
            "y0": 1044.64,
            "x1": 435.51,
            "y1": 1069.47,
            "width": 202.02,
            "height": 24.83
          },
          "engine": "docling"
        }
      ],
      "alternates": [],
      "review": {
        "status": "unreviewed",
        "risk": "high",
        "notes": ""
      }
    },
    {
      "id": "docling-eq-0005",
      "kind": "display",
      "display_latex": "(4)",
      "semantic_expr": null,
      "compiled_targets": {},
      "conversion": {
        "status": "unconverted",
        "notes": ""
      },
      "source_spans": [
        {
          "page": 13,
          "bbox": {
            "x0": 619.32,
            "y0": 256.61,
            "x1": 640.85,
            "y1": 273.16,
            "width": 21.53,
            "height": 16.55
          },
          "engine": "docling"
        }
      ],
      "alternates": [],
      "review": {
        "status": "unreviewed",
        "risk": "medium",
        "notes": ""
      },
      "equation_number": "(4)"
    },
    {
      "id": "docling-eq-0006",
      "kind": "display",
      "display_latex": "Si = (Sul there exists ek = Si1, 0 ≤ i ≤ N). (5)",
      "semantic_expr": null,
      "compiled_targets": {},
      "conversion": {
        "status": "unconverted",
        "notes": ""
      },
      "source_spans": [
        {
          "page": 13,
          "bbox": {
            "x0": 175.53,
            "y0": 1024.7,
            "x1": 640.85,
            "y1": 1049.69,
            "width": 465.32,
            "height": 24.99
          },
          "engine": "docling"
        }
      ],
      "alternates": [],
      "review": {
        "status": "unreviewed",
        "risk": "medium",
        "notes": ""
      },
      "equation_number": "(5)"
    },
    {
      "id": "docling-eq-0007",
      "kind": "display",
      "display_latex": "{Pijh≤ı≤N,1≤j≤N,, (6)",
      "semantic_expr": null,
      "compiled_targets": {},
      "conversion": {
        "status": "unconverted",
        "notes": ""
      },
      "source_spans": [
        {
          "page": 14,
          "bbox": {
            "x0": 266.61,
            "y0": 814.52,
            "x1": 639.19,
            "y1": 836.04,
            "width": 372.58,
            "height": 21.52
          },
          "engine": "docling"
        }
      ],
      "alternates": [],
      "review": {
        "status": "unreviewed",
        "risk": "medium",
        "notes": ""
      },
      "equation_number": "(6)"
    },
    {
      "id": "docling-eq-0008",
      "kind": "display",
      "display_latex": "$ (F, F) = area((F, U F\") - (FnE), F, F, ≤ R;. (7)",
      "semantic_expr": null,
      "compiled_targets": {},
      "conversion": {
        "status": "unconverted",
        "notes": ""
      },
      "source_spans": [
        {
          "page": 15,
          "bbox": {
            "x0": 125.85,
            "y0": 69.53,
            "x1": 642.5,
            "y1": 91.05,
            "width": 516.65,
            "height": 21.52
          },
          "engine": "docling"
        }
      ],
      "alternates": [],
      "review": {
        "status": "unreviewed",
        "risk": "medium",
        "notes": ""
      },
      "equation_number": "(7)"
    },
    {
      "id": "docling-eq-0009",
      "kind": "display",
      "display_latex": "(8)",
      "semantic_expr": null,
      "compiled_targets": {},
      "conversion": {
        "status": "unconverted",
        "notes": ""
      },
      "source_spans": [
        {
          "page": 15,
          "bbox": {
            "x0": 619.32,
            "y0": 392.36,
            "x1": 642.5,
            "y1": 410.57,
            "width": 23.18,
            "height": 18.21
          },
          "engine": "docling"
        }
      ],
      "alternates": [],
      "review": {
        "status": "unreviewed",
        "risk": "medium",
        "notes": ""
      },
      "equation_number": "(8)"
    },
    {
      "id": "docling-eq-0010",
      "kind": "display",
      "display_latex": "(Piy) = (patches generated from curve segments) U {patches from the two planes), (9)",
      "semantic_expr": null,
      "compiled_targets": {},
      "conversion": {
        "status": "unconverted",
        "notes": ""
      },
      "source_spans": [
        {
          "page": 15,
          "bbox": {
            "x0": 162.28,
            "y0": 789.68,
            "x1": 640.85,
            "y1": 839.42,
            "width": 478.57,
            "height": 49.74
          },
          "engine": "docling"
        }
      ],
      "alternates": [],
      "review": {
        "status": "unreviewed",
        "risk": "medium",
        "notes": ""
      },
      "equation_number": "(9)"
    }
  ]
}
