{
  "engine": "docling",
  "entries": [
    {
      "id": "docling-eq-0001",
      "kind": "display",
      "display_latex": "Sx =   -1 0 1 -2 0 2 -1 0 1   Sy =   -1 -2 -1 0 0 0 1 2 1   .",
      "semantic_expr": null,
      "compiled_targets": {},
      "conversion": {
        "status": "unconverted",
        "notes": ""
      },
      "source_spans": [
        {
          "page": 17,
          "bbox": {
            "x0": 181.45,
            "y0": 617.63,
            "x1": 430.56,
            "y1": 658.97,
            "width": 249.11,
            "height": 41.34
          },
          "engine": "docling"
        }
      ],
      "alternates": [],
      "review": {
        "status": "unreviewed",
        "risk": "high",
        "notes": ""
      }
    },
    {
      "id": "docling-eq-0002",
      "kind": "display",
      "display_latex": "G ( x , y ) = √ ( D ( x , y ) ⊗ Sx ) 2 +( D ( x , y ) ⊗ Sy ) 2 ,",
      "semantic_expr": null,
      "compiled_targets": {},
      "conversion": {
        "status": "unconverted",
        "notes": ""
      },
      "source_spans": [
        {
          "page": 17,
          "bbox": {
            "x0": 197.62,
            "y0": 704.96,
            "x1": 414.39,
            "y1": 723.28,
            "width": 216.77,
            "height": 18.32
          },
          "engine": "docling"
        }
      ],
      "alternates": [],
      "review": {
        "status": "unreviewed",
        "risk": "medium",
        "notes": ""
      }
    },
    {
      "id": "docling-eq-0003",
      "kind": "display",
      "display_latex": "Edge ( x , y ) = { 1 if G ( x , y ) ≥ t 0 if G ( x , y ) < t",
      "semantic_expr": null,
      "compiled_targets": {},
      "conversion": {
        "status": "unconverted",
        "notes": ""
      },
      "source_spans": [
        {
          "page": 19,
          "bbox": {
            "x0": 220.92,
            "y0": 136.46,
            "x1": 388.89,
            "y1": 169.37,
            "width": 167.97,
            "height": 32.91
          },
          "engine": "docling"
        }
      ],
      "alternates": [],
      "review": {
        "status": "unreviewed",
        "risk": "medium",
        "notes": ""
      }
    },
    {
      "id": "docling-eq-0004",
      "kind": "display",
      "display_latex": "z = z 0 z 1 ( d 1 -d 0 ) z 1 -z 0 d -( z 1 + z 0 )( d 1 -d 0 ) 2 ( z 1 -z 0 ) -d 1 + d 0 2",
      "semantic_expr": null,
      "compiled_targets": {},
      "conversion": {
        "status": "unconverted",
        "notes": ""
      },
      "source_spans": [
        {
          "page": 19,
          "bbox": {
            "x0": 235.06,
            "y0": 409.25,
            "x1": 374.05,
            "y1": 450.64,
            "width": 138.99,
            "height": 41.39
          },
          "engine": "docling"
        }
      ],
      "alternates": [],
      "review": {
        "status": "unreviewed",
        "risk": "medium",
        "notes": ""
      }
    },
    {
      "id": "docling-eq-0005",
      "kind": "display",
      "display_latex": "g ( s ) = v · s = vxs 1 + vys 2 + vzs 3 = 0 (3.1)",
      "semantic_expr": null,
      "compiled_targets": {},
      "conversion": {
        "status": "unconverted",
        "notes": ""
      },
      "source_spans": [
        {
          "page": 28,
          "bbox": {
            "x0": 221.02,
            "y0": 707.91,
            "x1": 522.0,
            "y1": 719.91,
            "width": 300.98,
            "height": 12.0
          },
          "engine": "docling"
        }
      ],
      "alternates": [],
      "review": {
        "status": "unreviewed",
        "risk": "medium",
        "notes": ""
      }
    },
    {
      "id": "docling-eq-0006",
      "kind": "display",
      "display_latex": "g ( s ) = ( cx , cy , cz , 1 ) · s = 0 .",
      "semantic_expr": null,
      "compiled_targets": {},
      "conversion": {
        "status": "unconverted",
        "notes": ""
      },
      "source_spans": [
        {
          "page": 30,
          "bbox": {
            "x0": 242.12,
            "y0": 430.22,
            "x1": 369.89,
            "y1": 441.99,
            "width": 127.77,
            "height": 11.77
          },
          "engine": "docling"
        }
      ],
      "alternates": [],
      "review": {
        "status": "unreviewed",
        "risk": "medium",
        "notes": ""
      }
    },
    {
      "id": "docling-eq-0007",
      "kind": "display",
      "display_latex": "n 1 = ± ( b -a ) × ( c -a ) || ( b -a ) × ( c -a ) || .",
      "semantic_expr": null,
      "compiled_targets": {},
      "conversion": {
        "status": "unconverted",
        "notes": ""
      },
      "source_spans": [
        {
          "page": 44,
          "bbox": {
            "x0": 238.62,
            "y0": 494.8,
            "x1": 373.39,
            "y1": 521.84,
            "width": 134.77,
            "height": 27.04
          },
          "engine": "docling"
        }
      ],
      "alternates": [],
      "review": {
        "status": "unreviewed",
        "risk": "medium",
        "notes": ""
      }
    },
    {
      "id": "docling-eq-0008",
      "kind": "display",
      "display_latex": "ˆ n i = j ∈ N ( i ) Aj n j j ∈ N ( i ) Aj n i = ˆ n i || ˆ n i ||",
      "semantic_expr": null,
      "compiled_targets": {},
      "conversion": {
        "status": "unconverted",
        "notes": ""
      },
      "source_spans": [
        {
          "page": 53,
          "bbox": {
            "x0": 262.97,
            "y0": 393.5,
            "x1": 347.11,
            "y1": 441.94,
            "width": 84.14,
            "height": 48.44
          },
          "engine": "docling"
        }
      ],
      "alternates": [],
      "review": {
        "status": "unreviewed",
        "risk": "medium",
        "notes": ""
      }
    },
    {
      "id": "docling-eq-0009",
      "kind": "display",
      "display_latex": "g ( p i ) = ( p i -c ) · n i .",
      "semantic_expr": null,
      "compiled_targets": {},
      "conversion": {
        "status": "unconverted",
        "notes": ""
      },
      "source_spans": [
        {
          "page": 53,
          "bbox": {
            "x0": 258.05,
            "y0": 522.39,
            "x1": 353.96,
            "y1": 534.17,
            "width": 95.91,
            "height": 11.78
          },
          "engine": "docling"
        }
      ],
      "alternates": [],
      "review": {
        "status": "unreviewed",
        "risk": "medium",
        "notes": ""
      }
    },
    {
      "id": "docling-eq-0010",
      "kind": "display",
      "display_latex": "g ( t ) = ( 1 -t ) g ( p i ) + tg ( p j ) .",
      "semantic_expr": null,
      "compiled_targets": {},
      "conversion": {
        "status": "unconverted",
        "notes": ""
      },
      "source_spans": [
        {
          "page": 53,
          "bbox": {
            "x0": 237.75,
            "y0": 712.25,
            "x1": 374.26,
            "y1": 724.02,
            "width": 136.51,
            "height": 11.77
          },
          "engine": "docling"
        }
      ],
      "alternates": [],
      "review": {
        "status": "unreviewed",
        "risk": "medium",
        "notes": ""
      }
    },
    {
      "id": "docling-eq-0011",
      "kind": "display",
      "display_latex": "t = g ( p i ) g ( p i ) -g ( p j ) , p ( t ) = ( 1 -t ) p i + t p j = g ( p i ) p i -g ( p j ) p j g ( p i ) -g ( p j ) . (6.1)",
      "semantic_expr": null,
      "compiled_targets": {},
      "conversion": {
        "status": "unconverted",
        "notes": ""
      },
      "source_spans": [
        {
          "page": 54,
          "bbox": {
            "x0": 201.76,
            "y0": 603.25,
            "x1": 522.0,
            "y1": 664.47,
            "width": 320.24,
            "height": 61.22
          },
          "engine": "docling"
        }
      ],
      "alternates": [],
      "review": {
        "status": "unreviewed",
        "risk": "medium",
        "notes": ""
      }
    },
    {
      "id": "docling-eq-0012",
      "kind": "display",
      "display_latex": "p ( u ) =   fx ( u , v ) fy ( u , v ) f z ( u , v )  ",
      "semantic_expr": null,
      "compiled_targets": {},
      "conversion": {
        "status": "unconverted",
        "notes": ""
      },
      "source_spans": [
        {
          "page": 59,
          "bbox": {
            "x0": 256.91,
            "y0": 563.94,
            "x1": 355.1,
            "y1": 606.32,
            "width": 98.19,
            "height": 42.38
          },
          "engine": "docling"
        }
      ],
      "alternates": [],
      "review": {
        "status": "unreviewed",
        "risk": "medium",
        "notes": ""
      }
    },
    {
      "id": "docling-eq-0013",
      "kind": "display",
      "display_latex": "p ( u , v ) = n i = 0 m i = 0 N k i ( u ) N l j ( v ) wi , j p i , j n i = 0 m i = 0 N k i ( u ) N l j ( v ) wi , j , (7.1)",
      "semantic_expr": null,
      "compiled_targets": {},
      "conversion": {
        "status": "unconverted",
        "notes": ""
      },
      "source_spans": [
        {
          "page": 59,
          "bbox": {
            "x0": 209.09,
            "y0": 691.25,
            "x1": 522.0,
            "y1": 726.33,
            "width": 312.91,
            "height": 35.08
          },
          "engine": "docling"
        }
      ],
      "alternates": [],
      "review": {
        "status": "unreviewed",
        "risk": "medium",
        "notes": ""
      }
    },
    {
      "id": "docling-eq-0014",
      "kind": "display",
      "display_latex": "t u ( u ) = ¶ p ¶ u ∣ ∣ ∣ ∣ u = [ ¶ fx ¶ u , ¶ fy ¶ u , ¶ f z ¶ u ] glyph[latticetop] t v ( u ) = ¶ p ¶ v ∣ ∣ ∣ ∣ u = [ ¶ fx ¶ v , ¶ fy ¶ v , ¶ f z ¶ v ] glyph[latticetop]",
      "semantic_expr": null,
      "compiled_targets": {},
      "conversion": {
        "status": "unconverted",
        "notes": ""
      },
      "source_spans": [
        {
          "page": 60,
          "bbox": {
            "x0": 130.53,
            "y0": 414.23,
            "x1": 480.98,
            "y1": 447.9,
            "width": 350.45,
            "height": 33.67
          },
          "engine": "docling"
        }
      ],
      "alternates": [],
      "review": {
        "status": "unreviewed",
        "risk": "high",
        "notes": ""
      }
    },
    {
      "id": "docling-eq-0015",
      "kind": "display",
      "display_latex": "n ( u ) = t u ( u ) × t v ( u ) ,",
      "semantic_expr": null,
      "compiled_targets": {},
      "conversion": {
        "status": "unconverted",
        "notes": ""
      },
      "source_spans": [
        {
          "page": 60,
          "bbox": {
            "x0": 254.82,
            "y0": 486.9,
            "x1": 357.19,
            "y1": 498.68,
            "width": 102.37,
            "height": 11.78
          },
          "engine": "docling"
        }
      ],
      "alternates": [],
      "review": {
        "status": "unreviewed",
        "risk": "medium",
        "notes": ""
      }
    },
    {
      "id": "docling-eq-0016",
      "kind": "display",
      "display_latex": "g ( u ) = ( p ( u ) -c ) · n ( u ) .",
      "semantic_expr": null,
      "compiled_targets": {},
      "conversion": {
        "status": "unconverted",
        "notes": ""
      },
      "source_spans": [
        {
          "page": 61,
          "bbox": {
            "x0": 246.61,
            "y0": 497.23,
            "x1": 365.4,
            "y1": 507.98,
            "width": 118.79,
            "height": 10.75
          },
          "engine": "docling"
        }
      ],
      "alternates": [],
      "review": {
        "status": "unreviewed",
        "risk": "medium",
        "notes": ""
      }
    },
    {
      "id": "docling-eq-0017",
      "kind": "display",
      "display_latex": "K = k r ( p ) k p ( p ) ‖ p -c ‖ .",
      "semantic_expr": null,
      "compiled_targets": {},
      "conversion": {
        "status": "unconverted",
        "notes": ""
      },
      "source_spans": [
        {
          "page": 65,
          "bbox": {
            "x0": 264.12,
            "y0": 399.13,
            "x1": 347.89,
            "y1": 426.37,
            "width": 83.77,
            "height": 27.24
          },
          "engine": "docling"
        }
      ],
      "alternates": [],
      "review": {
        "status": "unreviewed",
        "risk": "medium",
        "notes": ""
      }
    },
    {
      "id": "docling-eq-0018",
      "kind": "display",
      "display_latex": "S = { p ∈ R 3 | f ( p ) = r } ,",
      "semantic_expr": null,
      "compiled_targets": {},
      "conversion": {
        "status": "unconverted",
        "notes": ""
      },
      "source_spans": [
        {
          "page": 72,
          "bbox": {
            "x0": 243.85,
            "y0": 387.24,
            "x1": 368.17,
            "y1": 401.46,
            "width": 124.32,
            "height": 14.22
          },
          "engine": "docling"
        }
      ],
      "alternates": [],
      "review": {
        "status": "unreviewed",
        "risk": "medium",
        "notes": ""
      }
    },
    {
      "id": "docling-eq-0019",
      "kind": "display",
      "display_latex": "n = f ( p ) ‖ f ( p ) ‖ ,",
      "semantic_expr": null,
      "compiled_targets": {},
      "conversion": {
        "status": "unconverted",
        "notes": ""
      },
      "source_spans": [
        {
          "page": 72,
          "bbox": {
            "x0": 270.89,
            "y0": 516.53,
            "x1": 341.12,
            "y1": 543.57,
            "width": 70.23,
            "height": 27.04
          },
          "engine": "docling"
        }
      ],
      "alternates": [],
      "review": {
        "status": "unreviewed",
        "risk": "medium",
        "notes": ""
      }
    },
    {
      "id": "docling-eq-0020",
      "kind": "display",
      "display_latex": "f ( p ) = ( ¶ f ¶ x ∣ ∣ ∣ ∣ p , ¶ f ¶ y ∣ ∣ ∣ ∣ p , ¶ f ¶ z ∣ ∣ ∣ ∣ p ) glyph[latticetop] .",
      "semantic_expr": null,
      "compiled_targets": {},
      "conversion": {
        "status": "unconverted",
        "notes": ""
      },
      "source_spans": [
        {
          "page": 72,
          "bbox": {
            "x0": 230.93,
            "y0": 565.44,
            "x1": 391.39,
            "y1": 602.7,
            "width": 160.46,
            "height": 37.26
          },
          "engine": "docling"
        }
      ],
      "alternates": [],
      "review": {
        "status": "unreviewed",
        "risk": "high",
        "notes": ""
      }
    },
    {
      "id": "docling-eq-0021",
      "kind": "display",
      "display_latex": "k n ( t ) = t glyph[latticetop] ( n ) t ‖ t ‖ 2",
      "semantic_expr": null,
      "compiled_targets": {},
      "conversion": {
        "status": "unconverted",
        "notes": ""
      },
      "source_spans": [
        {
          "page": 72,
          "bbox": {
            "x0": 264.91,
            "y0": 633.88,
            "x1": 345.89,
            "y1": 665.03,
            "width": 80.98,
            "height": 31.15
          },
          "engine": "docling"
        }
      ],
      "alternates": [],
      "review": {
        "status": "unreviewed",
        "risk": "high",
        "notes": ""
      }
    },
    {
      "id": "docling-eq-0022",
      "kind": "display",
      "display_latex": "( f ( p ) -c ) · n = 0 ⇔ ( f ( p ) -c ) · f ( p ) = 0 ,",
      "semantic_expr": null,
      "compiled_targets": {},
      "conversion": {
        "status": "unconverted",
        "notes": ""
      },
      "source_spans": [
        {
          "page": 73,
          "bbox": {
            "x0": 237.47,
            "y0": 182.0,
            "x1": 374.54,
            "y1": 210.18,
            "width": 137.07,
            "height": 28.18
          },
          "engine": "docling"
        }
      ],
      "alternates": [],
      "review": {
        "status": "unreviewed",
        "risk": "medium",
        "notes": ""
      }
    },
    {
      "id": "docling-eq-0023",
      "kind": "display",
      "display_latex": "{ f ( c ( t )) = 0 v glyph[latticetop] f ( c ( t )) = 0 . 1 (8.1)",
      "semantic_expr": null,
      "compiled_targets": {},
      "conversion": {
        "status": "unconverted",
        "notes": ""
      },
      "source_spans": [
        {
          "page": 73,
          "bbox": {
            "x0": 257.23,
            "y0": 425.38,
            "x1": 522.0,
            "y1": 458.46,
            "width": 264.77,
            "height": 33.08
          },
          "engine": "docling"
        }
      ],
      "alternates": [],
      "review": {
        "status": "unreviewed",
        "risk": "high",
        "notes": ""
      }
    },
    {
      "id": "docling-eq-0024",
      "kind": "display",
      "display_latex": "{ f ( c ( t )) · w = 0 v glyph[latticetop] H f ( c ( t )) w = 0 .",
      "semantic_expr": null,
      "compiled_targets": {},
      "conversion": {
        "status": "unconverted",
        "notes": ""
      },
      "source_spans": [
        {
          "page": 73,
          "bbox": {
            "x0": 255.35,
            "y0": 502.39,
            "x1": 355.47,
            "y1": 535.47,
            "width": 100.12,
            "height": 33.08
          },
          "engine": "docling"
        }
      ],
      "alternates": [],
      "review": {
        "status": "unreviewed",
        "risk": "high",
        "notes": ""
      }
    },
    {
      "id": "docling-eq-0025",
      "kind": "display",
      "display_latex": "w f ( c ( t )) × v glyph[latticetop] H f .",
      "semantic_expr": null,
      "compiled_targets": {},
      "conversion": {
        "status": "unconverted",
        "notes": ""
      },
      "source_spans": [
        {
          "page": 73,
          "bbox": {
            "x0": 250.88,
            "y0": 584.63,
            "x1": 361.13,
            "y1": 598.19,
            "width": 110.25,
            "height": 13.56
          },
          "engine": "docling"
        }
      ],
      "alternates": [],
      "review": {
        "status": "unreviewed",
        "risk": "high",
        "notes": ""
      }
    },
    {
      "id": "docling-eq-0026",
      "kind": "display",
      "display_latex": "p i + 1 = p i + e F ( p i ) , with F ( p ) = f ( p ) × v glyph[latticetop] H f ( p ) .",
      "semantic_expr": null,
      "compiled_targets": {},
      "conversion": {
        "status": "unconverted",
        "notes": ""
      },
      "source_spans": [
        {
          "page": 73,
          "bbox": {
            "x0": 226.59,
            "y0": 670.07,
            "x1": 385.42,
            "y1": 700.32,
            "width": 158.83,
            "height": 30.25
          },
          "engine": "docling"
        }
      ],
      "alternates": [],
      "review": {
        "status": "unreviewed",
        "risk": "high",
        "notes": ""
      }
    },
    {
      "id": "docling-eq-0027",
      "kind": "display",
      "display_latex": "F surface ( p ) = -f ( p ) f ( p )) ‖ f ( p ) 2 ‖ .",
      "semantic_expr": null,
      "compiled_targets": {},
      "conversion": {
        "status": "unconverted",
        "notes": ""
      },
      "source_spans": [
        {
          "page": 74,
          "bbox": {
            "x0": 237.67,
            "y0": 349.12,
            "x1": 374.34,
            "y1": 376.16,
            "width": 136.67,
            "height": 27.04
          },
          "engine": "docling"
        }
      ],
      "alternates": [],
      "review": {
        "status": "unreviewed",
        "risk": "medium",
        "notes": ""
      }
    },
    {
      "id": "docling-eq-0028",
      "kind": "display",
      "display_latex": "F contour ( p ) = -( v · f ( p )) v glyph[latticetop] H f ( p ) ‖ f ( p ) 2 ‖ .",
      "semantic_expr": null,
      "compiled_targets": {},
      "conversion": {
        "status": "unconverted",
        "notes": ""
      },
      "source_spans": [
        {
          "page": 74,
          "bbox": {
            "x0": 217.21,
            "y0": 435.13,
            "x1": 394.8,
            "y1": 464.39,
            "width": 177.59,
            "height": 29.26
          },
          "engine": "docling"
        }
      ],
      "alternates": [],
      "review": {
        "status": "unreviewed",
        "risk": "high",
        "notes": ""
      }
    },
    {
      "id": "docling-eq-0029",
      "kind": "display",
      "display_latex": "p i + 1 = p i + e ( F ( p i ) + F surface ( p i ) + kF contour ( p i )) = p i + e ‖ f ( p i ) ‖ 2 ( f ( p i ) × v glyph[latticetop] H f ( p i ) -f ( p i ) f ( p i ))) -k ( v · f ( p i )) v glyph[latticetop] H f ( p i ))",
      "semantic_expr": null,
      "compiled_targets": {},
      "conversion": {
        "status": "unconverted",
        "notes": ""
      },
      "source_spans": [
        {
          "page": 74,
          "bbox": {
            "x0": 159.53,
            "y0": 496.95,
            "x1": 452.47,
            "y1": 559.55,
            "width": 292.94,
            "height": 62.6
          },
          "engine": "docling"
        }
      ],
      "alternates": [],
      "review": {
        "status": "unreviewed",
        "risk": "high",
        "notes": ""
      }
    },
    {
      "id": "docling-eq-0030",
      "kind": "display",
      "display_latex": "F ( p ) = f ( p ) × ( v × f ( p )) ‖ f ( p ) ‖ 2 ,",
      "semantic_expr": null,
      "compiled_targets": {},
      "conversion": {
        "status": "unconverted",
        "notes": ""
      },
      "source_spans": [
        {
          "page": 74,
          "bbox": {
            "x0": 232.18,
            "y0": 696.96,
            "x1": 379.83,
            "y1": 725.99,
            "width": 147.65,
            "height": 29.03
          },
          "engine": "docling"
        }
      ],
      "alternates": [],
      "review": {
        "status": "unreviewed",
        "risk": "medium",
        "notes": ""
      }
    },
    {
      "id": "docling-eq-0031",
      "kind": "display",
      "display_latex": "p ← p + ( f ( p ) -r ) f ( p ) ‖ f ( p ) ‖ .",
      "semantic_expr": null,
      "compiled_targets": {},
      "conversion": {
        "status": "unconverted",
        "notes": ""
      },
      "source_spans": [
        {
          "page": 77,
          "bbox": {
            "x0": 239.79,
            "y0": 463.05,
            "x1": 372.22,
            "y1": 490.09,
            "width": 132.43,
            "height": 27.04
          },
          "engine": "docling"
        }
      ],
      "alternates": [],
      "review": {
        "status": "unreviewed",
        "risk": "medium",
        "notes": ""
      }
    },
    {
      "id": "docling-eq-0032",
      "kind": "display",
      "display_latex": "vi jk = f ( p i jk ) = f ( xi , y j , zk ) . (8.2)",
      "semantic_expr": null,
      "compiled_targets": {},
      "conversion": {
        "status": "unconverted",
        "notes": ""
      },
      "source_spans": [
        {
          "page": 78,
          "bbox": {
            "x0": 238.08,
            "y0": 712.25,
            "x1": 522.0,
            "y1": 724.29,
            "width": 283.92,
            "height": 12.04
          },
          "engine": "docling"
        }
      ],
      "alternates": [],
      "review": {
        "status": "unreviewed",
        "risk": "medium",
        "notes": ""
      }
    },
    {
      "id": "docling-eq-0033",
      "kind": "display",
      "display_latex": "{ f ( p i jk ) -r = 0 f ( p i jk ) · v = 0",
      "semantic_expr": null,
      "compiled_targets": {},
      "conversion": {
        "status": "unconverted",
        "notes": ""
      },
      "source_spans": [
        {
          "page": 79,
          "bbox": {
            "x0": 262.08,
            "y0": 553.14,
            "x1": 348.72,
            "y1": 586.48,
            "width": 86.64,
            "height": 33.34
          },
          "engine": "docling"
        }
      ],
      "alternates": [],
      "review": {
        "status": "unreviewed",
        "risk": "medium",
        "notes": ""
      }
    },
    {
      "id": "docling-eq-0034",
      "kind": "display",
      "display_latex": "D ( u , v , w ) = i j k f ( p i jk ) N d i ( u ) N d j ( v ) N d k ( w ) ,",
      "semantic_expr": null,
      "compiled_targets": {},
      "conversion": {
        "status": "unconverted",
        "notes": ""
      },
      "source_spans": [
        {
          "page": 80,
          "bbox": {
            "x0": 192.13,
            "y0": 179.75,
            "x1": 419.88,
            "y1": 204.98,
            "width": 227.75,
            "height": 25.23
          },
          "engine": "docling"
        }
      ],
      "alternates": [],
      "review": {
        "status": "unreviewed",
        "risk": "medium",
        "notes": ""
      }
    },
    {
      "id": "docling-eq-0035",
      "kind": "display",
      "display_latex": "{ D -r = 0 D · v = 0",
      "semantic_expr": null,
      "compiled_targets": {},
      "conversion": {
        "status": "unconverted",
        "notes": ""
      },
      "source_spans": [
        {
          "page": 80,
          "bbox": {
            "x0": 274.75,
            "y0": 262.85,
            "x1": 336.05,
            "y1": 294.9,
            "width": 61.3,
            "height": 32.05
          },
          "engine": "docling"
        }
      ],
      "alternates": [],
      "review": {
        "status": "unreviewed",
        "risk": "medium",
        "notes": ""
      }
    },
    {
      "id": "docling-eq-0036",
      "kind": "display",
      "display_latex": "f ( p i jk ) = f ( xi , y j , zk ) ≈ 1 2    f ( xi + 1 , y j , zk ) -f ( xi -1 , y j , zk ) f ( xi , y j + 1 , zk ) -f ( xi , y j -1 , zk ) f ( xi , y j , zk + 1 ) -f ( xi , y j , zk -1 )    ,",
      "semantic_expr": null,
      "compiled_targets": {},
      "conversion": {
        "status": "unconverted",
        "notes": ""
      },
      "source_spans": [
        {
          "page": 82,
          "bbox": {
            "x0": 163.36,
            "y0": 129.61,
            "x1": 458.97,
            "y1": 178.96,
            "width": 295.61,
            "height": 49.35
          },
          "engine": "docling"
        }
      ],
      "alternates": [],
      "review": {
        "status": "unreviewed",
        "risk": "medium",
        "notes": ""
      }
    },
    {
      "id": "docling-eq-0037",
      "kind": "display",
      "display_latex": "a ′ i jk = a i jk ( ksc + kss ( 1 -| f ( p i jk ) · v | kse ) ,",
      "semantic_expr": null,
      "compiled_targets": {},
      "conversion": {
        "status": "unconverted",
        "notes": ""
      },
      "source_spans": [
        {
          "page": 82,
          "bbox": {
            "x0": 206.47,
            "y0": 314.57,
            "x1": 405.54,
            "y1": 330.94,
            "width": 199.07,
            "height": 16.37
          },
          "engine": "docling"
        }
      ],
      "alternates": [],
      "review": {
        "status": "unreviewed",
        "risk": "medium",
        "notes": ""
      }
    },
    {
      "id": "docling-eq-0038",
      "kind": "display",
      "display_latex": "ci jk = w ( | f ( p i jk ) | )( 1 -| f ( p i jk ) · v | ) kse ,",
      "semantic_expr": null,
      "compiled_targets": {},
      "conversion": {
        "status": "unconverted",
        "notes": ""
      },
      "source_spans": [
        {
          "page": 82,
          "bbox": {
            "x0": 205.42,
            "y0": 423.39,
            "x1": 406.59,
            "y1": 438.11,
            "width": 201.17,
            "height": 14.72
          },
          "engine": "docling"
        }
      ],
      "alternates": [],
      "review": {
        "status": "unreviewed",
        "risk": "medium",
        "notes": ""
      }
    },
    {
      "id": "docling-eq-0039",
      "kind": "display",
      "display_latex": "˜ n ( u , v ) = ( -k 1 u , -k 2 v , 1 ) glyph[latticetop] ,",
      "semantic_expr": null,
      "compiled_targets": {},
      "conversion": {
        "status": "unconverted",
        "notes": ""
      },
      "source_spans": [
        {
          "page": 84,
          "bbox": {
            "x0": 239.09,
            "y0": 333.48,
            "x1": 372.93,
            "y1": 348.29,
            "width": 133.84,
            "height": 14.81
          },
          "engine": "docling"
        }
      ],
      "alternates": [],
      "review": {
        "status": "unreviewed",
        "risk": "high",
        "notes": ""
      }
    },
    {
      "id": "docling-eq-0040",
      "kind": "display",
      "display_latex": "˜ v =( e1 · v , e2 · v , n · v ) glyph[latticetop] .",
      "semantic_expr": null,
      "compiled_targets": {},
      "conversion": {
        "status": "unconverted",
        "notes": ""
      },
      "source_spans": [
        {
          "page": 84,
          "bbox": {
            "x0": 248.52,
            "y0": 400.73,
            "x1": 363.49,
            "y1": 415.73,
            "width": 114.97,
            "height": 15.0
          },
          "engine": "docling"
        }
      ],
      "alternates": [],
      "review": {
        "status": "unreviewed",
        "risk": "high",
        "notes": ""
      }
    },
    {
      "id": "docling-eq-0041",
      "kind": "display",
      "display_latex": "˜ v · ˜ n ( u , v ) = 0 ⇔-k 1 ( e1 · v ) u -k 2 ( e2 · v ) v + n · v = 0 ,",
      "semantic_expr": null,
      "compiled_targets": {},
      "conversion": {
        "status": "unconverted",
        "notes": ""
      },
      "source_spans": [
        {
          "page": 84,
          "bbox": {
            "x0": 176.65,
            "y0": 458.83,
            "x1": 435.36,
            "y1": 471.02,
            "width": 258.71,
            "height": 12.19
          },
          "engine": "docling"
        }
      ],
      "alternates": [],
      "review": {
        "status": "unreviewed",
        "risk": "medium",
        "notes": ""
      }
    },
    {
      "id": "docling-eq-0042",
      "kind": "display",
      "display_latex": "d = -k 2 ( e2 · v ) e 1 + k 1 ( e1 · v ) e 2 .",
      "semantic_expr": null,
      "compiled_targets": {},
      "conversion": {
        "status": "unconverted",
        "notes": ""
      },
      "source_spans": [
        {
          "page": 84,
          "bbox": {
            "x0": 228.76,
            "y0": 506.16,
            "x1": 383.25,
            "y1": 518.34,
            "width": 154.49,
            "height": 12.18
          },
          "engine": "docling"
        }
      ],
      "alternates": [],
      "review": {
        "status": "unreviewed",
        "risk": "medium",
        "notes": ""
      }
    },
    {
      "id": "docling-eq-0043",
      "kind": "display",
      "display_latex": "T = ( n · v ) 2 √ ( k 1 ( e1 · v )) 2 +( k 2 ( e2 · v )) 2 .",
      "semantic_expr": null,
      "compiled_targets": {},
      "conversion": {
        "status": "unconverted",
        "notes": ""
      },
      "source_spans": [
        {
          "page": 84,
          "bbox": {
            "x0": 221.5,
            "y0": 590.88,
            "x1": 390.51,
            "y1": 623.17,
            "width": 169.01,
            "height": 32.29
          },
          "engine": "docling"
        }
      ],
      "alternates": [],
      "review": {
        "status": "unreviewed",
        "risk": "medium",
        "notes": ""
      }
    },
    {
      "id": "docling-eq-0044",
      "kind": "display",
      "display_latex": "r i = wi [ 0 -1 1 0 ] v i + 1 -v i -1 ‖ v i + 1 -v i -1 ‖ ,",
      "semantic_expr": null,
      "compiled_targets": {},
      "conversion": {
        "status": "unconverted",
        "notes": ""
      },
      "source_spans": [
        {
          "page": 88,
          "bbox": {
            "x0": 230.28,
            "y0": 641.3,
            "x1": 381.73,
            "y1": 670.59,
            "width": 151.45,
            "height": 29.29
          },
          "engine": "docling"
        }
      ],
      "alternates": [],
      "review": {
        "status": "unreviewed",
        "risk": "medium",
        "notes": ""
      }
    },
    {
      "id": "docling-eq-0045",
      "kind": "display",
      "display_latex": "n ( u ) = ¶ f ¶ u ∣ ∣ ∣ x = u × ¶ f ¶ v ∣ ∣ ∣ x = u ∥ ∥ ∥ ¶ f ¶ u ∣ ∣ ∣ x = u × ¶ f ¶ v ∣ ∣ ∣ x = u ∥ ∥ ∥ .",
      "semantic_expr": null,
      "compiled_targets": {},
      "conversion": {
        "status": "unconverted",
        "notes": ""
      },
      "source_spans": [
        {
          "page": 100,
          "bbox": {
            "x0": 236.43,
            "y0": 134.62,
            "x1": 375.58,
            "y1": 184.38,
            "width": 139.15,
            "height": 49.76
          },
          "engine": "docling"
        }
      ],
      "alternates": [],
      "review": {
        "status": "unreviewed",
        "risk": "high",
        "notes": ""
      }
    },
    {
      "id": "docling-eq-0046",
      "kind": "display",
      "display_latex": "d 2 c dt 2 = t ′ = -k n .",
      "semantic_expr": null,
      "compiled_targets": {},
      "conversion": {
        "status": "unconverted",
        "notes": ""
      },
      "source_spans": [
        {
          "page": 100,
          "bbox": {
            "x0": 266.08,
            "y0": 468.69,
            "x1": 347.13,
            "y1": 497.46,
            "width": 81.05,
            "height": 28.77
          },
          "engine": "docling"
        }
      ],
      "alternates": [],
      "review": {
        "status": "unreviewed",
        "risk": "medium",
        "notes": ""
      }
    },
    {
      "id": "docling-eq-0047",
      "kind": "display",
      "display_latex": "t ′ = -k n , n ′ = k t -t b , b ′ = t n .",
      "semantic_expr": null,
      "compiled_targets": {},
      "conversion": {
        "status": "unconverted",
        "notes": ""
      },
      "source_spans": [
        {
          "page": 100,
          "bbox": {
            "x0": 204.1,
            "y0": 709.44,
            "x1": 407.91,
            "y1": 723.33,
            "width": 203.81,
            "height": 13.89
          },
          "engine": "docling"
        }
      ],
      "alternates": [],
      "review": {
        "status": "unreviewed",
        "risk": "medium",
        "notes": ""
      }
    },
    {
      "id": "docling-eq-0048",
      "kind": "display",
      "display_latex": "k n ( t ) = t · n ′ ‖ t ‖ 2 .",
      "semantic_expr": null,
      "compiled_targets": {},
      "conversion": {
        "status": "unconverted",
        "notes": ""
      },
      "source_spans": [
        {
          "page": 102,
          "bbox": {
            "x0": 272.99,
            "y0": 267.71,
            "x1": 339.02,
            "y1": 296.97,
            "width": 66.03,
            "height": 29.26
          },
          "engine": "docling"
        }
      ],
      "alternates": [],
      "review": {
        "status": "unreviewed",
        "risk": "medium",
        "notes": ""
      }
    },
    {
      "id": "docling-eq-0049",
      "kind": "display",
      "display_latex": "S ( ei ) = k i ei .",
      "semantic_expr": null,
      "compiled_targets": {},
      "conversion": {
        "status": "unconverted",
        "notes": ""
      },
      "source_spans": [
        {
          "page": 102,
          "bbox": {
            "x0": 276.29,
            "y0": 492.08,
            "x1": 335.72,
            "y1": 504.27,
            "width": 59.43,
            "height": 12.19
          },
          "engine": "docling"
        }
      ],
      "alternates": [],
      "review": {
        "status": "unreviewed",
        "risk": "medium",
        "notes": ""
      }
    },
    {
      "id": "docling-eq-0050",
      "kind": "display",
      "display_latex": "K = k 1 k 2 ,",
      "semantic_expr": null,
      "compiled_targets": {},
      "conversion": {
        "status": "unconverted",
        "notes": ""
      },
      "source_spans": [
        {
          "page": 102,
          "bbox": {
            "x0": 281.18,
            "y0": 545.5,
            "x1": 330.83,
            "y1": 557.41,
            "width": 49.65,
            "height": 11.91
          },
          "engine": "docling"
        }
      ],
      "alternates": [],
      "review": {
        "status": "unreviewed",
        "risk": "medium",
        "notes": ""
      }
    },
    {
      "id": "docling-eq-0051",
      "kind": "display",
      "display_latex": "H = k 1 + k 2 2 .",
      "semantic_expr": null,
      "compiled_targets": {},
      "conversion": {
        "status": "unconverted",
        "notes": ""
      },
      "source_spans": [
        {
          "page": 102,
          "bbox": {
            "x0": 273.26,
            "y0": 594.88,
            "x1": 338.75,
            "y1": 621.82,
            "width": 65.49,
            "height": 26.94
          },
          "engine": "docling"
        }
      ],
      "alternates": [],
      "review": {
        "status": "unreviewed",
        "risk": "medium",
        "notes": ""
      }
    },
    {
      "id": "docling-eq-0052",
      "kind": "display",
      "display_latex": "I ( x , y ) = x · y .",
      "semantic_expr": null,
      "compiled_targets": {},
      "conversion": {
        "status": "unconverted",
        "notes": ""
      },
      "source_spans": [
        {
          "page": 103,
          "bbox": {
            "x0": 272.49,
            "y0": 296.26,
            "x1": 339.52,
            "y1": 307.01,
            "width": 67.03,
            "height": 10.75
          },
          "engine": "docling"
        }
      ],
      "alternates": [],
      "review": {
        "status": "unreviewed",
        "risk": "medium",
        "notes": ""
      }
    },
    {
      "id": "docling-eq-0053",
      "kind": "display",
      "display_latex": "II ( x , y ) = S ( x ) · y = S ( y ) · x .",
      "semantic_expr": null,
      "compiled_targets": {},
      "conversion": {
        "status": "unconverted",
        "notes": ""
      },
      "source_spans": [
        {
          "page": 103,
          "bbox": {
            "x0": 238.22,
            "y0": 349.06,
            "x1": 373.79,
            "y1": 359.81,
            "width": 135.57,
            "height": 10.75
          },
          "engine": "docling"
        }
      ],
      "alternates": [],
      "review": {
        "status": "unreviewed",
        "risk": "medium",
        "notes": ""
      }
    },
    {
      "id": "docling-eq-0054",
      "kind": "display",
      "display_latex": "k n = II ( t , t ) I ( t , t ) .",
      "semantic_expr": null,
      "compiled_targets": {},
      "conversion": {
        "status": "unconverted",
        "notes": ""
      },
      "source_spans": [
        {
          "page": 103,
          "bbox": {
            "x0": 274.48,
            "y0": 399.97,
            "x1": 337.52,
            "y1": 427.01,
            "width": 63.04,
            "height": 27.04
          },
          "engine": "docling"
        }
      ],
      "alternates": [],
      "review": {
        "status": "unreviewed",
        "risk": "medium",
        "notes": ""
      }
    },
    {
      "id": "docling-eq-0055",
      "kind": "display",
      "display_latex": "II ( x , y ) = x glyph[latticetop] [ k 1 0 0 k 2 ] y .",
      "semantic_expr": null,
      "compiled_targets": {},
      "conversion": {
        "status": "unconverted",
        "notes": ""
      },
      "source_spans": [
        {
          "page": 103,
          "bbox": {
            "x0": 240.61,
            "y0": 498.72,
            "x1": 371.4,
            "y1": 526.93,
            "width": 130.79,
            "height": 28.21
          },
          "engine": "docling"
        }
      ],
      "alternates": [],
      "review": {
        "status": "unreviewed",
        "risk": "high",
        "notes": ""
      }
    },
    {
      "id": "docling-eq-0056",
      "kind": "display",
      "display_latex": "k n ( q ) = k 1 cos 2 q + k 2 sin 2 q .",
      "semantic_expr": null,
      "compiled_targets": {},
      "conversion": {
        "status": "unconverted",
        "notes": ""
      },
      "source_spans": [
        {
          "page": 103,
          "bbox": {
            "x0": 234.8,
            "y0": 578.14,
            "x1": 377.21,
            "y1": 592.66,
            "width": 142.41,
            "height": 14.52
          },
          "engine": "docling"
        }
      ],
      "alternates": [],
      "review": {
        "status": "unreviewed",
        "risk": "medium",
        "notes": ""
      }
    },
    {
      "id": "docling-eq-0057",
      "kind": "display",
      "display_latex": "ORIENT3D ( a , b , c , d ) = # ad · ( # bd × # cd ) = det ( # ad , # bd , # cd ) = ∣ ∣ ∣ ∣ ∣ ∣ ax -dx ay -dy az -dz bx -dx by -dy bz -dz cx -dx cy -dy cz -dz ∣ ∣ ∣ ∣ ∣ ∣ = ∣ ∣ ∣ ∣ ∣ ∣ ∣ ∣ ax ay az 1 bx by bz 1 cx cy cz 1 dx dy dz 1 ∣ ∣ ∣ ∣ ∣ ∣ ∣ ∣",
      "semantic_expr": null,
      "compiled_targets": {},
      "conversion": {
        "status": "unconverted",
        "notes": ""
      },
      "source_spans": [
        {
          "page": 108,
          "bbox": {
            "x0": 178.3,
            "y0": 207.28,
            "x1": 434.01,
            "y1": 354.12,
            "width": 255.71,
            "height": 146.84
          },
          "engine": "docling"
        }
      ],
      "alternates": [],
      "review": {
        "status": "unreviewed",
        "risk": "high",
        "notes": ""
      }
    },
    {
      "id": "docling-eq-0058",
      "kind": "display",
      "display_latex": "SAMESIDE ( a , b , c , d , e ) =( ORIENT3D ( a , b , c , d ) > 0 ) == ( ORIENT3D ( a , b , c , e ) > 0 )",
      "semantic_expr": null,
      "compiled_targets": {},
      "conversion": {
        "status": "unconverted",
        "notes": ""
      },
      "source_spans": [
        {
          "page": 108,
          "bbox": {
            "x0": 153.95,
            "y0": 464.4,
            "x1": 458.36,
            "y1": 492.58,
            "width": 304.41,
            "height": 28.18
          },
          "engine": "docling"
        }
      ],
      "alternates": [],
      "review": {
        "status": "unreviewed",
        "risk": "medium",
        "notes": ""
      }
    },
    {
      "id": "docling-eq-0059",
      "kind": "display",
      "display_latex": "FRONTSIDE ( a , b , c , d ) = # da · n = # da · ( # ba × # ca ) = det ( # da , # ba , # ca ) = ORIENT3D ( d , b , c , a ) = -ORIENT3D ( a , b , c , d )",
      "semantic_expr": null,
      "compiled_targets": {},
      "conversion": {
        "status": "unconverted",
        "notes": ""
      },
      "source_spans": [
        {
          "page": 108,
          "bbox": {
            "x0": 188.4,
            "y0": 571.01,
            "x1": 423.91,
            "y1": 661.73,
            "width": 235.51,
            "height": 90.72
          },
          "engine": "docling"
        }
      ],
      "alternates": [],
      "review": {
        "status": "unreviewed",
        "risk": "medium",
        "notes": ""
      }
    }
  ]
}
